{
"meta":{"test_sets":[],"test_metrics":[],"learn_metrics":[{"best_value":"Min","name":"RMSE"}],"launch_mode":"Train","parameters":"","iteration_count":190,"learn_sets":["learn"],"name":"experiment"},
"iterations":[
{"learn":[3.149228502],"iteration":0,"passed_time":0.05344362859,"remaining_time":10.1008458},
{"learn":[3.090679588],"iteration":1,"passed_time":0.09737000956,"remaining_time":9.152780899},
{"learn":[3.033049905],"iteration":2,"passed_time":0.1741678914,"remaining_time":10.85646523},
{"learn":[2.982428193],"iteration":3,"passed_time":0.2431230873,"remaining_time":11.30522356},
{"learn":[2.934574401],"iteration":4,"passed_time":0.337661741,"remaining_time":12.49348442},
{"learn":[2.889224081],"iteration":5,"passed_time":0.376222487,"remaining_time":11.5374896},
{"learn":[2.847030071],"iteration":6,"passed_time":0.4113868679,"remaining_time":10.75482812},
{"learn":[2.810254642],"iteration":7,"passed_time":0.4340485542,"remaining_time":9.874604608},
{"learn":[2.770751644],"iteration":8,"passed_time":0.4569861251,"remaining_time":9.190498738},
{"learn":[2.731209743],"iteration":9,"passed_time":0.4747950911,"remaining_time":8.546311639},
{"learn":[2.698160854],"iteration":10,"passed_time":0.4944680581,"remaining_time":8.046343855},
{"learn":[2.664881165],"iteration":11,"passed_time":0.5159745,"remaining_time":7.653621751},
{"learn":[2.636096239],"iteration":12,"passed_time":0.5372766441,"remaining_time":7.315228155},
{"learn":[2.605754392],"iteration":13,"passed_time":0.5617037132,"remaining_time":7.061418108},
{"learn":[2.577020556],"iteration":14,"passed_time":0.5947697933,"remaining_time":6.938980922},
{"learn":[2.546134923],"iteration":15,"passed_time":0.6285057251,"remaining_time":6.834999761},
{"learn":[2.520210578],"iteration":16,"passed_time":0.6525816939,"remaining_time":6.640978415},
{"learn":[2.495524353],"iteration":17,"passed_time":0.6714559312,"remaining_time":6.416134453},
{"learn":[2.474635349],"iteration":18,"passed_time":0.6929948548,"remaining_time":6.236953694},
{"learn":[2.45376381],"iteration":19,"passed_time":0.7109030921,"remaining_time":6.042676283},
{"learn":[2.43431105],"iteration":20,"passed_time":0.7301845892,"remaining_time":5.876247409},
{"learn":[2.417556168],"iteration":21,"passed_time":0.7509490683,"remaining_time":5.734520158},
{"learn":[2.399960547],"iteration":22,"passed_time":0.7706646145,"remaining_time":5.595695244},
{"learn":[2.385069085],"iteration":23,"passed_time":0.7958459695,"remaining_time":5.504601289},
{"learn":[2.36569773],"iteration":24,"passed_time":0.8187752217,"remaining_time":5.403916463},
{"learn":[2.350610081],"iteration":25,"passed_time":0.8424346606,"remaining_time":5.313818628},
{"learn":[2.33448862],"iteration":26,"passed_time":0.8630239907,"remaining_time":5.210107796},
{"learn":[2.320612576],"iteration":27,"passed_time":0.883875068,"remaining_time":5.113848608},
{"learn":[2.307910552],"iteration":28,"passed_time":0.9070297256,"remaining_time":5.035578821},
{"learn":[2.295141613],"iteration":29,"passed_time":0.9299348996,"remaining_time":4.959652798},
{"learn":[2.282666741],"iteration":30,"passed_time":0.9495735542,"remaining_time":4.870393391},
{"learn":[2.27051805],"iteration":31,"passed_time":0.9700489559,"remaining_time":4.78961672},
{"learn":[2.257541847],"iteration":32,"passed_time":0.992243767,"remaining_time":4.720674891},
{"learn":[2.245592871],"iteration":33,"passed_time":1.014660835,"remaining_time":4.655502657},
{"learn":[2.233378863],"iteration":34,"passed_time":1.037385048,"remaining_time":4.594133783},
{"learn":[2.221715874],"iteration":35,"passed_time":1.059014391,"remaining_time":4.530228229},
{"learn":[2.211263332],"iteration":36,"passed_time":1.07987259,"remaining_time":4.465419089},
{"learn":[2.20137011],"iteration":37,"passed_time":1.098986896,"remaining_time":4.395947583},
{"learn":[2.19129929],"iteration":38,"passed_time":1.121203166,"remaining_time":4.341068669},
{"learn":[2.182667999],"iteration":39,"passed_time":1.143129883,"remaining_time":4.286737062},
{"learn":[2.176489681],"iteration":40,"passed_time":1.169730372,"remaining_time":4.250971352},
{"learn":[2.168069979],"iteration":41,"passed_time":1.18948755,"remaining_time":4.191527558},
{"learn":[2.158841565],"iteration":42,"passed_time":1.210423922,"remaining_time":4.137960851},
{"learn":[2.150145498],"iteration":43,"passed_time":1.235459153,"remaining_time":4.099478098},
{"learn":[2.143089941],"iteration":44,"passed_time":1.256581252,"remaining_time":4.048984034},
{"learn":[2.134890014],"iteration":45,"passed_time":1.274750893,"remaining_time":3.990524534},
{"learn":[2.127992046],"iteration":46,"passed_time":1.298730744,"remaining_time":3.95145737},
{"learn":[2.121228868],"iteration":47,"passed_time":1.322021788,"remaining_time":3.910981124},
{"learn":[2.113879604],"iteration":48,"passed_time":1.368460934,"remaining_time":3.937816158},
{"learn":[2.108463304],"iteration":49,"passed_time":1.414464161,"remaining_time":3.96049965},
{"learn":[2.102831389],"iteration":50,"passed_time":1.443567849,"remaining_time":3.934430021},
{"learn":[2.096306387],"iteration":51,"passed_time":1.46196648,"remaining_time":3.87983412},
{"learn":[2.091307517],"iteration":52,"passed_time":1.479332558,"remaining_time":3.823935103},
{"learn":[2.089167262],"iteration":53,"passed_time":1.495059423,"remaining_time":3.765334842},
{"learn":[2.083171695],"iteration":54,"passed_time":1.513423547,"remaining_time":3.714766889},
{"learn":[2.078117644],"iteration":55,"passed_time":1.530800736,"remaining_time":3.662987476},
{"learn":[2.074404517],"iteration":56,"passed_time":1.548171386,"remaining_time":3.6123999},
{"learn":[2.067605975],"iteration":57,"passed_time":1.566277446,"remaining_time":3.564631429},
{"learn":[2.063300098],"iteration":58,"passed_time":1.585279891,"remaining_time":3.519858741},
{"learn":[2.058701391],"iteration":59,"passed_time":1.604787305,"remaining_time":3.477039162},
{"learn":[2.054428213],"iteration":60,"passed_time":1.623003631,"remaining_time":3.43225358},
{"learn":[2.04914827],"iteration":61,"passed_time":1.643345449,"remaining_time":3.392713185},
{"learn":[2.044352198],"iteration":62,"passed_time":1.66521853,"remaining_time":3.3568691},
{"learn":[2.037941771],"iteration":63,"passed_time":1.687869964,"remaining_time":3.322993991},
{"learn":[2.03440007],"iteration":64,"passed_time":1.710266941,"remaining_time":3.288974886},
{"learn":[2.030751017],"iteration":65,"passed_time":1.731362875,"remaining_time":3.252863584},
{"learn":[2.025908939],"iteration":66,"passed_time":1.752457405,"remaining_time":3.217197923},
{"learn":[2.023930891],"iteration":67,"passed_time":1.775434649,"remaining_time":3.185338635},
{"learn":[2.019474084],"iteration":68,"passed_time":1.796635522,"remaining_time":3.150621713},
{"learn":[2.014819538],"iteration":69,"passed_time":1.815106137,"remaining_time":3.111610521},
{"learn":[2.011369314],"iteration":70,"passed_time":1.83480546,"remaining_time":3.07523732},
{"learn":[2.007180831],"iteration":71,"passed_time":1.854439228,"remaining_time":3.039219847},
{"learn":[2.00343327],"iteration":72,"passed_time":1.873420535,"remaining_time":3.002605516},
{"learn":[2.000625866],"iteration":73,"passed_time":1.89284916,"remaining_time":2.967168954},
{"learn":[1.998184876],"iteration":74,"passed_time":1.910158956,"remaining_time":2.928910399},
{"learn":[1.99691337],"iteration":75,"passed_time":1.916417123,"remaining_time":2.874625685},
{"learn":[1.993845418],"iteration":76,"passed_time":1.935185532,"remaining_time":2.839947599},
{"learn":[1.988606088],"iteration":77,"passed_time":1.952976333,"remaining_time":2.804273709},
{"learn":[1.987016198],"iteration":78,"passed_time":1.971375451,"remaining_time":2.769907279},
{"learn":[1.983323543],"iteration":79,"passed_time":1.988089173,"remaining_time":2.733622614},
{"learn":[1.979618627],"iteration":80,"passed_time":2.006027046,"remaining_time":2.699468495},
{"learn":[1.976321999],"iteration":81,"passed_time":2.022068314,"remaining_time":2.663211926},
{"learn":[1.972891632],"iteration":82,"passed_time":2.041084602,"remaining_time":2.63127774},
{"learn":[1.968839176],"iteration":83,"passed_time":2.060583829,"remaining_time":2.600260546},
{"learn":[1.965617414],"iteration":84,"passed_time":2.078461194,"remaining_time":2.567510887},
{"learn":[1.962207424],"iteration":85,"passed_time":2.096654203,"remaining_time":2.535488804},
{"learn":[1.960787946],"iteration":86,"passed_time":2.11538129,"remaining_time":2.504416929},
{"learn":[1.958074676],"iteration":87,"passed_time":2.13377378,"remaining_time":2.473237791},
{"learn":[1.956514217],"iteration":88,"passed_time":2.148845027,"remaining_time":2.438576941},
{"learn":[1.95305939],"iteration":89,"passed_time":2.166409766,"remaining_time":2.407121963},
{"learn":[1.950166351],"iteration":90,"passed_time":2.184135412,"remaining_time":2.376147317},
{"learn":[1.948471467],"iteration":91,"passed_time":2.201916106,"remaining_time":2.34551933},
{"learn":[1.945507308],"iteration":92,"passed_time":2.221285901,"remaining_time":2.31682508},
{"learn":[1.94156732],"iteration":93,"passed_time":2.238482426,"remaining_time":2.286109711},
{"learn":[1.939464569],"iteration":94,"passed_time":2.255934671,"remaining_time":2.255934671},
{"learn":[1.937945101],"iteration":95,"passed_time":2.273308504,"remaining_time":2.22594791},
{"learn":[1.935114788],"iteration":96,"passed_time":2.291655383,"remaining_time":2.19715413},
{"learn":[1.933520071],"iteration":97,"passed_time":2.310664488,"remaining_time":2.169195234},
{"learn":[1.930626175],"iteration":98,"passed_time":2.329276763,"remaining_time":2.141052378},
{"learn":[1.927388974],"iteration":99,"passed_time":2.345558112,"remaining_time":2.111002301},
{"learn":[1.923964423],"iteration":100,"passed_time":2.363948342,"remaining_time":2.083083193},
{"learn":[1.921073823],"iteration":101,"passed_time":2.382089424,"remaining_time":2.055135974},
{"learn":[1.917790739],"iteration":102,"passed_time":2.400854691,"remaining_time":2.027906389},
{"learn":[1.915046763],"iteration":103,"passed_time":2.420189838,"remaining_time":2.001310827},
{"learn":[1.911894594],"iteration":104,"passed_time":2.436613458,"remaining_time":1.972496609},
{"learn":[1.910871128],"iteration":105,"passed_time":2.441709002,"remaining_time":1.934939209},
{"learn":[1.906523474],"iteration":106,"passed_time":2.462250694,"remaining_time":1.909970165},
{"learn":[1.904917673],"iteration":107,"passed_time":2.483983308,"remaining_time":1.885987326},
{"learn":[1.903881633],"iteration":108,"passed_time":2.509192622,"remaining_time":1.86462938},
{"learn":[1.902572925],"iteration":109,"passed_time":2.531002983,"remaining_time":1.840729442},
{"learn":[1.899052262],"iteration":110,"passed_time":2.553064013,"remaining_time":1.817045559},
{"learn":[1.895386743],"iteration":111,"passed_time":2.647714953,"remaining_time":1.843944342},
{"learn":[1.892546955],"iteration":112,"passed_time":2.678735644,"remaining_time":1.825333138},
{"learn":[1.890116011],"iteration":113,"passed_time":2.703052459,"remaining_time":1.802034973},
{"learn":[1.889141081],"iteration":114,"passed_time":2.705502609,"remaining_time":1.764458223},
{"learn":[1.88722183],"iteration":115,"passed_time":2.727492657,"remaining_time":1.739952212},
{"learn":[1.883708221],"iteration":116,"passed_time":2.74770456,"remaining_time":1.714379768},
{"learn":[1.881358205],"iteration":117,"passed_time":2.767452514,"remaining_time":1.688615093},
{"learn":[1.879017724],"iteration":118,"passed_time":2.789198537,"remaining_time":1.664143665},
{"learn":[1.876790087],"iteration":119,"passed_time":2.807560452,"remaining_time":1.637743597},
{"learn":[1.874717749],"iteration":120,"passed_time":2.825204586,"remaining_time":1.611067078},
{"learn":[1.873745008],"iteration":121,"passed_time":2.843792153,"remaining_time":1.585064479},
{"learn":[1.871540932],"iteration":122,"passed_time":2.864630125,"remaining_time":1.560408279},
{"learn":[1.868448788],"iteration":123,"passed_time":2.885815376,"remaining_time":1.535998507},
{"learn":[1.86629738],"iteration":124,"passed_time":2.907623854,"remaining_time":1.511964404},
{"learn":[1.862737558],"iteration":125,"passed_time":2.931203039,"remaining_time":1.488865035},
{"learn":[1.861513044],"iteration":126,"passed_time":2.950448605,"remaining_time":1.463608363},
{"learn":[1.86023063],"iteration":127,"passed_time":2.972114412,"remaining_time":1.439617918},
{"learn":[1.859064813],"iteration":128,"passed_time":2.992420088,"remaining_time":1.415020351},
{"learn":[1.857727641],"iteration":129,"passed_time":3.013755268,"remaining_time":1.39096397},
{"learn":[1.854962143],"iteration":130,"passed_time":3.031824759,"remaining_time":1.365478327},
{"learn":[1.852681854],"iteration":131,"passed_time":3.0520258,"remaining_time":1.341041639},
{"learn":[1.848479802],"iteration":132,"passed_time":3.070875258,"remaining_time":1.316089396},
{"learn":[1.845394909],"iteration":133,"passed_time":3.09095812,"remaining_time":1.291743692},
{"learn":[1.843682217],"iteration":134,"passed_time":3.108661498,"remaining_time":1.266491722},
{"learn":[1.841091405],"iteration":135,"passed_time":3.125840069,"remaining_time":1.24114238},
{"learn":[1.83973072],"iteration":136,"passed_time":3.144304359,"remaining_time":1.216409715},
{"learn":[1.835980019],"iteration":137,"passed_time":3.163523091,"remaining_time":1.192052179},
{"learn":[1.834848574],"iteration":138,"passed_time":3.183657271,"remaining_time":1.168104466},
{"learn":[1.83202581],"iteration":139,"passed_time":3.202537631,"remaining_time":1.14376344},
{"learn":[1.830382334],"iteration":140,"passed_time":3.220568429,"remaining_time":1.119204631},
{"learn":[1.829319828],"iteration":141,"passed_time":3.237348344,"remaining_time":1.094314933},
{"learn":[1.826333269],"iteration":142,"passed_time":3.255514473,"remaining_time":1.069994267},
{"learn":[1.825099391],"iteration":143,"passed_time":3.273077601,"remaining_time":1.045566456},
{"learn":[1.822002107],"iteration":144,"passed_time":3.291311154,"remaining_time":1.021441393},
{"learn":[1.819326342],"iteration":145,"passed_time":3.310079328,"remaining_time":0.9975581537},
{"learn":[1.81681222],"iteration":146,"passed_time":3.328242976,"remaining_time":0.9735676732},
{"learn":[1.816005153],"iteration":147,"passed_time":3.345305101,"remaining_time":0.9493433394},
{"learn":[1.814583974],"iteration":148,"passed_time":3.362023326,"remaining_time":0.9251205124},
{"learn":[1.813564135],"iteration":149,"passed_time":3.382215345,"remaining_time":0.901924092},
{"learn":[1.809836712],"iteration":150,"passed_time":3.403195878,"remaining_time":0.8789711209},
{"learn":[1.807023609],"iteration":151,"passed_time":3.42168871,"remaining_time":0.8554221774},
{"learn":[1.806425658],"iteration":152,"passed_time":3.439311152,"remaining_time":0.8317288406},
{"learn":[1.805276402],"iteration":153,"passed_time":3.457600174,"remaining_time":0.8082701706},
{"learn":[1.804026473],"iteration":154,"passed_time":3.475701746,"remaining_time":0.7848358781},
{"learn":[1.802672259],"iteration":155,"passed_time":3.494946078,"remaining_time":0.7617190171},
{"learn":[1.800757499],"iteration":156,"passed_time":3.514828471,"remaining_time":0.7387856021},
{"learn":[1.799466759],"iteration":157,"passed_time":3.530550655,"remaining_time":0.7150482339},
{"learn":[1.798496128],"iteration":158,"passed_time":3.549528932,"remaining_time":0.6920465214},
{"learn":[1.795703905],"iteration":159,"passed_time":3.56626707,"remaining_time":0.6686750757},
{"learn":[1.793294337],"iteration":160,"passed_time":3.585886828,"remaining_time":0.6459050809},
{"learn":[1.791909943],"iteration":161,"passed_time":3.605188077,"remaining_time":0.6231189269},
{"learn":[1.791066124],"iteration":162,"passed_time":3.623474907,"remaining_time":0.6002074999},
{"learn":[1.789192388],"iteration":163,"passed_time":3.641528851,"remaining_time":0.5773155495},
{"learn":[1.786772198],"iteration":164,"passed_time":3.660406271,"remaining_time":0.5546070108},
{"learn":[1.783788553],"iteration":165,"passed_time":3.680521011,"remaining_time":0.5321235196},
{"learn":[1.782940687],"iteration":166,"passed_time":3.697715141,"remaining_time":0.5092661571},
{"learn":[1.781716574],"iteration":167,"passed_time":3.716033783,"remaining_time":0.4866234716},
{"learn":[1.77865284],"iteration":168,"passed_time":3.734965784,"remaining_time":0.4641081744},
{"learn":[1.776185837],"iteration":169,"passed_time":3.753329985,"remaining_time":0.4415682335},
{"learn":[1.773399504],"iteration":170,"passed_time":3.771602703,"remaining_time":0.4190669671},
{"learn":[1.772860123],"iteration":171,"passed_time":3.790113327,"remaining_time":0.3966397668},
{"learn":[1.771244655],"iteration":172,"passed_time":3.81045753,"remaining_time":0.3744380232},
{"learn":[1.770634919],"iteration":173,"passed_time":3.831362352,"remaining_time":0.3523091818},
{"learn":[1.767466787],"iteration":174,"passed_time":3.852004015,"remaining_time":0.3301717727},
{"learn":[1.766421972],"iteration":175,"passed_time":3.871228629,"remaining_time":0.3079386409},
{"learn":[1.765018829],"iteration":176,"passed_time":3.889991653,"remaining_time":0.2857056016},
{"learn":[1.763632138],"iteration":177,"passed_time":3.907923222,"remaining_time":0.2634554981},
{"learn":[1.762957462],"iteration":178,"passed_time":3.925597402,"remaining_time":0.2412378292},
{"learn":[1.760528383],"iteration":179,"passed_time":3.942714996,"remaining_time":0.219039722},
{"learn":[1.758524378],"iteration":180,"passed_time":3.961238682,"remaining_time":0.1969676693},
{"learn":[1.756023104],"iteration":181,"passed_time":3.97846369,"remaining_time":0.1748775248},
{"learn":[1.753168498],"iteration":182,"passed_time":3.997105299,"remaining_time":0.1528947382},
{"learn":[1.750479995],"iteration":183,"passed_time":4.015368548,"remaining_time":0.1309359309},
{"learn":[1.749159164],"iteration":184,"passed_time":4.032984419,"remaining_time":0.1089995789},
{"learn":[1.745739978],"iteration":185,"passed_time":4.051829383,"remaining_time":0.08713611576},
{"learn":[1.743609375],"iteration":186,"passed_time":4.070038119,"remaining_time":0.06529472919},
{"learn":[1.740741247],"iteration":187,"passed_time":4.087055143,"remaining_time":0.04347931003},
{"learn":[1.739898365],"iteration":188,"passed_time":4.105380124,"remaining_time":0.02172158796},
{"learn":[1.7377482],"iteration":189,"passed_time":4.125088284,"remaining_time":0}
]}